README.md
setup.py
plaindl/__init__.py
plaindl/tensor.py
plaindl.egg-info/PKG-INFO
plaindl.egg-info/SOURCES.txt
plaindl.egg-info/dependency_links.txt
plaindl.egg-info/not-zip-safe
plaindl.egg-info/requires.txt
plaindl.egg-info/top_level.txt