Metadata-Version: 1.0
Name: plaindl
Version: 0.1
Summary: a lightweight deep learning train framework with numpy
Home-page: https://gitee.com/li_zhuo_hua/plaindl
Author: ZH Li
Author-email: li199807@mail.ustc.edu.cn
License: Apache-2.0
Platform: UNKNOWN
